getSector.py
getSector-1.0.4.dist-info/METADATA
getSector-1.0.4.dist-info/WHEEL
getSector-1.0.4.dist-info/top_level.txt
getSector-1.0.4.dist-info/RECORD
