Metadata-Version: 2.1
Name: getSector
Version: 1.0.4
Summary: Nabla getWindSector Script
Author: Julen Gasco
Classifier: Programming Language :: Python :: 3
Classifier: License :: OSI Approved :: MIT License
Classifier: Operating System :: OS Independent
Requires-Python: >=3.6
